README.md
setup.py
blu_lib_trend.egg-info/PKG-INFO
blu_lib_trend.egg-info/SOURCES.txt
blu_lib_trend.egg-info/dependency_links.txt
blu_lib_trend.egg-info/requires.txt
blu_lib_trend.egg-info/top_level.txt
blu_trend/__init__.py
blu_trend/daum_trend.py
blu_trend/melon_chart.py
blu_trend/naver_trend.py
blu_trend/trend_to_json_parser.py