Metadata-Version: 1.0
Name: blu-lib-trend
Version: 0.2.8
Summary: get trend package
Home-page: UNKNOWN
Author: UNKNOWN
Author-email: master@bluehack.net
License: UNKNOWN
Keywords: blu,blu-lib-trend
Platform: UNKNOWN
